evar/__init__.py
evar/__main__.py
evar-0.1.0.dist-info/entry_points.txt
evar-0.1.0.dist-info/LICENSE
evar-0.1.0.dist-info/WHEEL
evar-0.1.0.dist-info/METADATA
evar-0.1.0.dist-info/RECORD
