Metadata-Version: 2.1
Name: evar
Version: 0.1.0
Summary: EVAR – Einfach vorlesen auf'm Reader 
Home-page: https://codeberg.org/Marix/evar
License: UNKNOWN
Author: Matthias Bach
Author-email: marix@marix.org
Classifier: License :: OSI Approved :: GNU General Public License v3 or later (GPLv3+)
Requires-Dist: requests_html
